genie_tts/GetPhonesAndBert.py
genie_tts/Internal.py
genie_tts/ModelManager.py
genie_tts/PredefinedCharacter.py
genie_tts/Server.py
genie_tts/__init__.py
genie_tts/Audio/Audio.py
genie_tts/Audio/ReferenceAudio.py
genie_tts/Audio/__init__.py
genie_tts/Converter/Converter.py
genie_tts/Converter/__init__.py
genie_tts/Converter/load_state_dict.py
genie_tts/Converter/utils.py
genie_tts/Converter/v2/Converter.py
genie_tts/Converter/v2/EncoderConverter.py
genie_tts/Converter/v2/T2SConverter.py
genie_tts/Converter/v2/VITSConverter.py
genie_tts/Converter/v2/__init__.py
genie_tts/Converter/v2ProPlus/Converter.py
genie_tts/Converter/v2ProPlus/PromptEncoderConverter.py
genie_tts/Core/Inference.py
genie_tts/Core/Resources.py
genie_tts/Core/TTSPlayer.py
genie_tts/Core/__init__.py
genie_tts/Data/v2/Keys/t2s_onnx_keys.txt
genie_tts/Data/v2/Keys/vits_onnx_keys.txt
genie_tts/Data/v2/Models/t2s_encoder_fp32.onnx
genie_tts/Data/v2/Models/t2s_first_stage_decoder_fp32.onnx
genie_tts/Data/v2/Models/t2s_stage_decoder_fp32.onnx
genie_tts/Data/v2/Models/vits_fp32.onnx
genie_tts/Data/v2ProPlus/Keys/prompt_encoder_weights.txt
genie_tts/Data/v2ProPlus/Keys/vits_weights.txt
genie_tts/Data/v2ProPlus/Models/prompt_encoder_fp32.onnx
genie_tts/Data/v2ProPlus/Models/vits_fp32.onnx
genie_tts/G2P/SymbolsV2.py
genie_tts/G2P/__init__.py
genie_tts/G2P/Chinese/ChineseG2P.py
genie_tts/G2P/Chinese/CorrectPronunciation.py
genie_tts/G2P/Chinese/Erhua.py
genie_tts/G2P/Chinese/ToneSandhi.py
genie_tts/G2P/Chinese/__init__.py
genie_tts/G2P/Chinese/Normalization/__init__.py
genie_tts/G2P/Chinese/Normalization/char_convert.py
genie_tts/G2P/Chinese/Normalization/chronology.py
genie_tts/G2P/Chinese/Normalization/constants.py
genie_tts/G2P/Chinese/Normalization/num.py
genie_tts/G2P/Chinese/Normalization/phonecode.py
genie_tts/G2P/Chinese/Normalization/quantifier.py
genie_tts/G2P/Chinese/Normalization/text_normlization.py
genie_tts/G2P/English/EnglishG2P.py
genie_tts/G2P/English/Normalization.py
genie_tts-2.0.2.dist-info/licenses/LICENSE
genie_tts-2.0.2.dist-info/METADATA
genie_tts-2.0.2.dist-info/WHEEL
genie_tts-2.0.2.dist-info/top_level.txt
genie_tts-2.0.2.dist-info/RECORD
